owl2yarrrml/__init__.py
owl2yarrrml/__main__.py
owl2yarrrml/constants.py
owl2yarrrml/translate.py
owl2yarrrml-1.2.dist-info/LICENSE
owl2yarrrml-1.2.dist-info/METADATA
owl2yarrrml-1.2.dist-info/WHEEL
owl2yarrrml-1.2.dist-info/RECORD
