Metadata-Version: 2.3
Name: owl2yarrrml
Version: 1.2
Summary: A Python library for translating OWL ontologies into YARRRML mappings
License: MIT
Keywords: owl,yarrrml,rdf,mapping,ontology
Author: David Chaves
Author-email: david.chaves@usc.es
Requires-Python: >3.8.1,<4.0.0
Classifier: License :: OSI Approved :: MIT License
Classifier: Programming Language :: Python :: 3
Classifier: Programming Language :: Python :: 3.9
Classifier: Programming Language :: Python :: 3.10
Classifier: Programming Language :: Python :: 3.11
Classifier: Programming Language :: Python :: 3.12
Classifier: Programming Language :: Python :: 3.13
Requires-Dist: PyYAML (>=6.0,<7.0)
Requires-Dist: owlready2 (>=0.39.0,<0.40.0)
Requires-Dist: rdflib (>=7.1.4,<8.0.0)
Project-URL: Homepage, https://github.com/citius/owl2yarrrml
Project-URL: Repository, https://github.com/citius/owl2yarrrml
